jupyterlab_day/__init__.py
jupyterlab_day/_version.py
jupyterlab_day-0.2.0.data/data/share/jupyter/labextensions/jupyterlab-day/package.json
jupyterlab_day-0.2.0.data/data/share/jupyter/labextensions/jupyterlab-day/static/509.ebcda1beacf7e3a7fa33.js
jupyterlab_day-0.2.0.data/data/share/jupyter/labextensions/jupyterlab-day/static/remoteEntry.3f1f2c2f968e3047b04d.js
jupyterlab_day-0.2.0.data/data/share/jupyter/labextensions/jupyterlab-day/static/style.js
jupyterlab_day-0.2.0.data/data/share/jupyter/labextensions/jupyterlab-day/static/third-party-licenses.json
jupyterlab_day-0.2.0.data/data/share/jupyter/labextensions/jupyterlab-day/themes/jupyterlab-day/index.css
jupyterlab_day-0.2.0.data/data/share/jupyter/labextensions/jupyterlab-day/themes/jupyterlab-day/index.js
jupyterlab_day-0.2.0.data/data/share/jupyter/labextensions/jupyterlab-day/install.json
jupyterlab_day-0.2.0.dist-info/METADATA
jupyterlab_day-0.2.0.dist-info/WHEEL
jupyterlab_day-0.2.0.dist-info/licenses/LICENSE
jupyterlab_day-0.2.0.dist-info/RECORD
