Metadata-Version: 2.4
Name: jupyterlab_day
Version: 0.2.0
Summary: Dark theme for JupyterLab
Project-URL: Homepage, https://github.com/jupyterlab-contrib/jupyterlab-day
Project-URL: Bug Tracker, https://github.com/jupyterlab-contrib/jupyterlab-day/issues
Project-URL: Repository, https://github.com/jupyterlab-contrib/jupyterlab-day.git
Author-email: Martin Renou <martin.renou@gmail.com>
License: BSD 3-Clause License
License-File: LICENSE
Keywords: jupyter,jupyterlab,jupyterlab-extension
Classifier: Framework :: Jupyter
Classifier: Framework :: Jupyter :: JupyterLab
Classifier: Framework :: Jupyter :: JupyterLab :: 4
Classifier: Framework :: Jupyter :: JupyterLab :: Extensions
Classifier: Framework :: Jupyter :: JupyterLab :: Extensions :: Prebuilt
Classifier: Framework :: Jupyter :: JupyterLab :: Extensions :: Themes
Classifier: License :: OSI Approved :: BSD License
Classifier: Programming Language :: Python
Classifier: Programming Language :: Python :: 3
Classifier: Programming Language :: Python :: 3.8
Classifier: Programming Language :: Python :: 3.9
Classifier: Programming Language :: Python :: 3.10
Classifier: Programming Language :: Python :: 3.11
Classifier: Programming Language :: Python :: 3.12
Requires-Python: >=3.8
